{
    "adminTemplate.calculatedError": "Cannot be CALCULATED together with: ",
    "adminTemplate.cancel": "Cancel",
    "adminTemplate.canNotDropColumn": "Cannot drop column here",
    "adminTemplate.change": "(Change)",
    "adminTemplate.columnDescriptionTooLong": "Column description is too long!",
    "adminTemplate.columnDisplayMismatch": "This column should be displayed/not displayed together with: ",
    "adminTemplate.columnDisplayMismatch": "This column should be displayed/not displayed together with: ",
    "adminTemplate.columnLabelEmpty": "Column label cannot be empty!",
    "adminTemplate.columnLabelNotAllowedCharacters": "Columns label can only have alpha-numeric characters!",
    "adminTemplate.columnLabelToShort": "Column label must have at least 2 characters",
    "adminTemplate.configureRnrTemplate": "Configure R&R template",
    "adminTemplate.definition": "Definition",
    "adminTemplate.display": "Display",
    "adminTemplate.dropError": "Cannot drop column here",
    "adminTemplate.emptyColumnOption": "Option cannot be empty!",
    "adminTemplate.emptyColumnSource": "Source cannot be empty!",
    "adminTemplate.emptyNumberOfPeriods": "Number of periods cannot be empty!",
    "adminTemplate.emptyNumberOfPeriods": "Number of periods cannot be empty!",
    "adminTemplate.invalidNumberOfPeriods": "Number of periods to average must be greater than or equal to 2",
    "adminTemplate.invalidNumberOfPeriods": "Number of periods to average must be greater than or equal to 2",
    "adminTemplate.isUserInput": " if source is USER INPUT",
    "adminTemplate.label": "Label",
    "adminTemplate.numberOfPeriodsToAverage": "Number of periods to average:",
    "adminTemplate.numberOfPeriodsToAverage": "Number of periods to average:",
    "adminTemplate.optionEmpty": "Option cannot be empty!",
    "adminTemplate.program": "Program",
    "adminTemplate.save": "Save",
    "adminTemplate.shouldBeDisplayed": "Should be displayed",
    "adminTemplate.shouldBeDisplayedIfOtherIsCalculated": "Should be displayed when ${column} is calculated.",
    "adminTemplate.source": "Source",
    "adminTemplate.sourceEmpty": "Source cannot be empty!",
    "adminTemplate.templateSave.failure": "Template save failed!",
    "adminTemplate.templateSave.success": "Template saved successfully!"
}
